LICENSE
README.md
setup.py
caffe2onnx/__init__.py
caffe2onnx/convert.py
caffe2onnx.egg-info/PKG-INFO
caffe2onnx.egg-info/SOURCES.txt
caffe2onnx.egg-info/dependency_links.txt
caffe2onnx.egg-info/requires.txt
caffe2onnx.egg-info/top_level.txt
caffe2onnx/proto/__init__.py
caffe2onnx/proto/caffe_upsample_pb2.py
caffe2onnx/src/__init__.py
caffe2onnx/src/args_parser.py
caffe2onnx/src/c2oObject.py
caffe2onnx/src/caffe2onnx.py
caffe2onnx/src/load_save_model.py
caffe2onnx/src/op_layer_info.py
caffe2onnx/src/utils.py
caffe2onnx/src/OPs/Add.py
caffe2onnx/src/OPs/Axpy.py
caffe2onnx/src/OPs/BatchNorm.py
caffe2onnx/src/OPs/Clip.py
caffe2onnx/src/OPs/Concat.py
caffe2onnx/src/OPs/Conv.py
caffe2onnx/src/OPs/ConvTranspose.py
caffe2onnx/src/OPs/Crop.py
caffe2onnx/src/OPs/DetectionOutput.py
caffe2onnx/src/OPs/Dropout.py
caffe2onnx/src/OPs/Eltwise.py
caffe2onnx/src/OPs/Flatten.py
caffe2onnx/src/OPs/Gemm.py
caffe2onnx/src/OPs/InstanceNorm.py
caffe2onnx/src/OPs/Interp.py
caffe2onnx/src/OPs/LRN.py
caffe2onnx/src/OPs/Log.py
caffe2onnx/src/OPs/LpNormalization.py
caffe2onnx/src/OPs/Min.py
caffe2onnx/src/OPs/Mul.py
caffe2onnx/src/OPs/PRelu.py
caffe2onnx/src/OPs/Pooling.py
caffe2onnx/src/OPs/Power.py
caffe2onnx/src/OPs/PriroBox.py
caffe2onnx/src/OPs/ReLU.py
caffe2onnx/src/OPs/Reshape.py
caffe2onnx/src/OPs/Resize.py
caffe2onnx/src/OPs/Shuffle.py
caffe2onnx/src/OPs/Sigmoid.py
caffe2onnx/src/OPs/Slice.py
caffe2onnx/src/OPs/Softmax.py
caffe2onnx/src/OPs/Tanh.py
caffe2onnx/src/OPs/Transpose.py
caffe2onnx/src/OPs/UnPooling.py
caffe2onnx/src/OPs/Upsample.py
caffe2onnx/src/OPs/__init__.py