Metadata-Version: 2.1
Name: caffe2onnx
Version: 2.0.1
Summary: Convert Caffe models to ONNX.
Home-page: https://github.com/asiryan/caffe-onnx
Author: Valery Asiryan
Author-email: dmc5mod@yandex.ru
License: BSD-3
Platform: UNKNOWN
Classifier: Topic :: Software Development :: Libraries
Classifier: Intended Audience :: Science/Research
Classifier: Intended Audience :: Developers
Classifier: License :: OSI Approved :: BSD License
Classifier: Operating System :: OS Independent
Classifier: Programming Language :: Python :: 3.5
Classifier: Programming Language :: Python :: 3.6
Classifier: Programming Language :: Python :: 3.7
Classifier: Programming Language :: Python :: 3.8
Classifier: Programming Language :: Python :: 3.9
Classifier: Programming Language :: Python :: 3.10
Classifier: Topic :: Scientific/Engineering :: Artificial Intelligence
Requires-Python: >=3.5
